{
    "id": 75206202,
    "name": "Firework",
    "author": "Vernam",
    "creators": ["Vernam"],
    "verifier": "Trick",
    "verification": "https://youtu.be/QBe5x2o9v2w",
    "percentToQualify": 72,
    "password": "Not Copyable",
    "records": [
         {
            "user": "Crisis",
            "link": "https://www.youtube.com/watch?v=diNjkbqdxYE",
            "percent": 100,
            "hz": 360
        },
        {
            "user": "Gokill",
            "link": "https://www.youtube.com/watch?v=keVlE1KsJDE",
            "percent": 100,
            "hz": 360
        },
       {
            "user": "Hover",
            "link": "https://www.youtube.com/watch?v=bfZq2Jpa1YE",
            "percent": 100,
            "hz": 360
        },
        {
            "user": "PowerGreen",
            "link": "https://www.youtube.com/watch?v=pcuUQYJu4ZE",
            "percent": 100,
            "hz": 60
        }        
    ]
}
